plugo/__init__.py
plugo/__main__.py
plugo/cli/__init__.py
plugo/cli/cookiecutter-api-plugin/__init__.py
plugo/cli/cookiecutter-api-plugin/cookiecutter.json
plugo/cli/cookiecutter-api-plugin/hooks/__init__.py
plugo/cli/cookiecutter-api-plugin/hooks/post_gen_project.py
plugo/cli/cookiecutter-api-plugin/{{cookiecutter.plugin_slug}}/__init__.py
plugo/cli/cookiecutter-api-plugin/{{cookiecutter.plugin_slug}}/api/__init__.py
plugo/cli/cookiecutter-api-plugin/{{cookiecutter.plugin_slug}}/api/rest_api/__init__.py
plugo/cli/cookiecutter-api-plugin/{{cookiecutter.plugin_slug}}/api/rest_api/routes.py
plugo/cli/cookiecutter-api-plugin/{{cookiecutter.plugin_slug}}/api/rest_api/{{cookiecutter.plugin_slug}}_controller.py
plugo/cli/cookiecutter-api-plugin/{{cookiecutter.plugin_slug}}/metadata.json
plugo/cli/cookiecutter-api-plugin/{{cookiecutter.plugin_slug}}/plugin.py
plugo/cli/cookiecutter-api-plugin/{{cookiecutter.plugin_slug}}/requirements.txt
plugo/cli/cookiecutter-api-plugin/{{cookiecutter.plugin_slug}}/services/__init__.py
plugo/cli/cookiecutter-api-plugin/{{cookiecutter.plugin_slug}}/services/{{cookiecutter.plugin_slug}}_service.py
plugo/cli/cookiecutter-api-plugin/{{cookiecutter.plugin_slug}}/utils/__init__.py
plugo/cli/cookiecutter-base-plugin/__init__.py
plugo/cli/cookiecutter-base-plugin/cookiecutter.json
plugo/cli/cookiecutter-base-plugin/hooks/__init__.py
plugo/cli/cookiecutter-base-plugin/hooks/post_gen_project.py
plugo/cli/cookiecutter-base-plugin/{{cookiecutter.plugin_slug}}/__init__.py
plugo/cli/cookiecutter-base-plugin/{{cookiecutter.plugin_slug}}/metadata.json
plugo/cli/cookiecutter-base-plugin/{{cookiecutter.plugin_slug}}/plugin.py
plugo/cli/cookiecutter-base-plugin/{{cookiecutter.plugin_slug}}/requirements.txt
plugo/cli/cookiecutter-ui-plugin/__init__.py
plugo/cli/cookiecutter-ui-plugin/cookiecutter.json
plugo/cli/cookiecutter-ui-plugin/hooks/__init__.py
plugo/cli/cookiecutter-ui-plugin/hooks/post_gen_project.py
plugo-4.1.2.dist-info/METADATA
plugo-4.1.2.dist-info/WHEEL
plugo-4.1.2.dist-info/entry_points.txt
plugo-4.1.2.dist-info/licenses/LICENSE
plugo-4.1.2.dist-info/RECORD
