Metadata-Version: 2.4
Name: plugo
Version: 4.1.2
Summary: Is a simple plugin manager that will dynamically load plugins from a directory given a config or env variable with dynamic kwargs to pass for plugin loading.
License: MIT
License-File: LICENSE
Author: Ryan Julyan
Author-email: ryan@julyan.biz
Requires-Python: >=3.10,<4.0
Classifier: License :: OSI Approved :: MIT License
Classifier: Programming Language :: Python
Classifier: Programming Language :: Python :: 3
Classifier: Programming Language :: Python :: 3.10
Classifier: Programming Language :: Python :: 3.11
Classifier: Programming Language :: Python :: 3.12
Classifier: Programming Language :: Python :: 3.13
Classifier: Programming Language :: Python :: 3.14
Provides-Extra: flask
Requires-Dist: Flask (>=3.0.3,<4.0.0) ; extra == "flask"
Requires-Dist: Flask-SQLAlchemy (>=3.1.1,<4.0.0) ; extra == "flask"
Requires-Dist: click (>=8.1.7,<9.0.0)
Requires-Dist: cookiecutter (>=2.6.0,<3.0.0)
Requires-Dist: dicttoxml (>=1.7.16,<2.0.0) ; extra == "flask"
Requires-Dist: flask-restx (>=1.3.0,<2.0.0) ; extra == "flask"
Requires-Dist: packaging (>=24.2,<25.0)
Requires-Dist: setuptools (>=75.3.0,<76.0.0)
Requires-Dist: tomli (>=2.3.0,<3.0.0)
Requires-Dist: watchdog (>=6.0.0,<7.0.0)
Project-URL: Homepage, https://github.com/RyanJulyan/plugo
Project-URL: Repository, https://github.com/RyanJulyan/plugo
